odoo/addons/res_partner_email_etd/README.rst
odoo/addons/res_partner_email_etd/__init__.py
odoo/addons/res_partner_email_etd/__manifest__.py
odoo/addons/res_partner_email_etd/i18n/es_CL.po
odoo/addons/res_partner_email_etd/i18n/res_partner_email_etd.pot
odoo/addons/res_partner_email_etd/models/__init__.py
odoo/addons/res_partner_email_etd/models/res_partner.py
odoo/addons/res_partner_email_etd/readme/CONTRIBUTORS.rst
odoo/addons/res_partner_email_etd/readme/DESCRIPTION.rst
odoo/addons/res_partner_email_etd/readme/USAGE.rst
odoo/addons/res_partner_email_etd/static/description/icon.png
odoo/addons/res_partner_email_etd/static/description/index.html
odoo/addons/res_partner_email_etd/views/res_partner.xml
odoo12_addon_res_partner_email_etd-12.0.1.0.0.99.dev7.dist-info/METADATA
odoo12_addon_res_partner_email_etd-12.0.1.0.0.99.dev7.dist-info/WHEEL
odoo12_addon_res_partner_email_etd-12.0.1.0.0.99.dev7.dist-info/top_level.txt
odoo12_addon_res_partner_email_etd-12.0.1.0.0.99.dev7.dist-info/RECORD
